[
	{
		"title": "Lorem ipsum dolor sit",
		"text": "Lorem ipsum dolor sit amet, consectetur adipisicing elit. Numquam dignissimos, atque rerum porro sapiente aperiam cupiditate tenetur. Tenetur fugiat, suscipit.",
		"date": [12, "Jan", 2016],
		"link": "#",
		"views": 542,
		"comments": 17
	},
	{
		"title": "Non, consectetur",
		"text": "Lorem ipsum dolor sit amet, consectetur adipisicing elit. Delectus beatae libero dolores eum architecto, quidem ipsa autem eveniet.",
		"date": [13, "Jan", 2016],
		"link": "#",
		"views": 992,
		"comments": 42 
	},
	{
		"title": "Labore magnam mollitia",
		"text": "Lorem ipsum dolor sit amet, consectetur adipisicing elit. Eos magni adipisci recusandae.",
		"date": [14, "Jan", 2016],
		"link": "#",
		"views": 1560,
		"comments": 98
	}
]